MANIFEST.in
README.md
setup.cfg
setup.py
pro_net_algorithm.egg-info/PKG-INFO
pro_net_algorithm.egg-info/SOURCES.txt
pro_net_algorithm.egg-info/dependency_links.txt
pro_net_algorithm.egg-info/top_level.txt
pronet_algorithm/__init__.py
pronet_algorithm/algorithm.py
test/test_algorithm.py